dynacli/__init__.py
dynacli/dynacli.py
dynacli/bootstrap/__init__.py
dynacli/bootstrap/_cli.py
dynacli/bootstrap/_sample_cli
dynacli/bootstrap/init.py
dynacli-1.0.8.dist-info/entry_points.txt
dynacli-1.0.8.dist-info/LICENSE.md
dynacli-1.0.8.dist-info/WHEEL
dynacli-1.0.8.dist-info/METADATA
dynacli-1.0.8.dist-info/RECORD
